pyfris/__init__.py
pyfris/fris_api.py
pyfris-0.0.2.dist-info/METADATA
pyfris-0.0.2.dist-info/WHEEL
pyfris-0.0.2.dist-info/licenses/LICENSE
pyfris-0.0.2.dist-info/RECORD
