Metadata-Version: 2.3
Name: pyfris
Version: 0.0.2
Summary: FRIS Python API
Project-URL: Homepage, https://github.com/guyanik/pyfris
Project-URL: Issues, https://github.com/guyanik/pyfris/issues
Author-email: Görkem Uyanık <uyanikhg@gmail.com>
License-Expression: MIT
License-File: LICENSE
Keywords: api,flanders,fris,information,pyfris,python,research,soap,space
Classifier: Development Status :: 3 - Alpha
Classifier: Intended Audience :: Developers
Classifier: Intended Audience :: Science/Research
Classifier: License :: OSI Approved :: MIT License
Classifier: Operating System :: OS Independent
Classifier: Programming Language :: Python :: 3
Classifier: Topic :: Scientific/Engineering
Classifier: Topic :: Scientific/Engineering :: Information Analysis
Classifier: Topic :: Software Development :: Libraries :: Python Modules
Requires-Python: >=3.8
